brainbase/__init__.py
brainbase/brainbase.py
brainbase-0.1.1.dist-info/METADATA
brainbase-0.1.1.dist-info/WHEEL
brainbase-0.1.1.dist-info/top_level.txt
brainbase-0.1.1.dist-info/RECORD
