Metadata-Version: 2.1
Name: brainbase
Version: 0.1.1
Summary: Brainbase Python SDK
Home-page: https://github.com/brainbasehq
Author: Gokhan Egri
Author-email: gokhan@usebrainbase.xyz
License: BSD 2-clause
Classifier: Development Status :: 1 - Planning
Classifier: Intended Audience :: Science/Research
Classifier: License :: OSI Approved :: BSD License
Classifier: Operating System :: POSIX :: Linux
Classifier: Programming Language :: Python :: 2
Classifier: Programming Language :: Python :: 2.7
Classifier: Programming Language :: Python :: 3
Classifier: Programming Language :: Python :: 3.4
Classifier: Programming Language :: Python :: 3.5
